{
    "beku.py": {
        "branch": "0.0.10",
        "description": "Test suite expander for Stackable Kuttl tests.",
        "homepage": null,
        "owner": "stackabletech",
        "repo": "beku.py",
        "rev": "fc75202a38529a4ac6776dd8a5dfee278d927f58",
        "sha256": "152yary0p11h87yabv74jnwkghsal7lx16az0qlzrzdrs6n5v8id",
        "type": "tarball",
        "url": "https://github.com/stackabletech/beku.py/archive/fc75202a38529a4ac6776dd8a5dfee278d927f58.tar.gz",
        "url_template": "https://github.com/<owner>/<repo>/archive/<rev>.tar.gz"
    },
    "nixpkgs": {
        "branch": "nixos-unstable",
        "description": "Nix Packages collection",
        "homepage": null,
        "owner": "NixOS",
        "repo": "nixpkgs",
        "rev": "3e3afe5174c561dee0df6f2c2b2236990146329f",
        "sha256": "0dcslr2lwfaclfl4pmbwb3yw27bnvwlqiif394d3d66vyd163dvy",
        "type": "tarball",
        "url": "https://github.com/NixOS/nixpkgs/archive/3e3afe5174c561dee0df6f2c2b2236990146329f.tar.gz",
        "url_template": "https://github.com/<owner>/<repo>/archive/<rev>.tar.gz"
    },
    "stackable-cockpit": {
        "branch": "main",
        "description": "Home of stackable-cockpit, stackablectl and stackable-cockpitd",
        "homepage": "https://docs.stackable.tech/management/stable/",
        "owner": "stackabletech",
        "repo": "stackable-cockpit",
        "rev": "e645c5c6ce42dc4eb06e0639e696cc2607011b32",
        "sha256": "09zfx2x3gdmpn1c2ri0z0h42qi53lg09rn54vpv90kcr33l7n4sg",
        "type": "tarball",
        "url": "https://github.com/stackabletech/stackable-cockpit/archive/e645c5c6ce42dc4eb06e0639e696cc2607011b32.tar.gz",
        "url_template": "https://github.com/<owner>/<repo>/archive/<rev>.tar.gz"
    }
}
